paddle_quantum/__init__.py
paddle_quantum/base.py
paddle_quantum/dataset.py
paddle_quantum/fisher.py
paddle_quantum/gradtool.py
paddle_quantum/hamiltonian.py
paddle_quantum/intrinsic.py
paddle_quantum/linalg.py
paddle_quantum/model.py
paddle_quantum/qinfo.py
paddle_quantum/shadow.py
paddle_quantum/trotter.py
paddle_quantum/visual.py
paddle_quantum/GIBBS/HGenerator.py
paddle_quantum/GIBBS/Paddle_GIBBS.py
paddle_quantum/GIBBS/example/main.py
paddle_quantum/QAOA/maxcut.py
paddle_quantum/QAOA/tsp.py
paddle_quantum/QAOA/example/main.py
paddle_quantum/SSVQE/HGenerator.py
paddle_quantum/SSVQE/Paddle_SSVQE.py
paddle_quantum/SSVQE/example/main.py
paddle_quantum/VQE/Paddle_VQE.py
paddle_quantum/VQE/benchmark.py
paddle_quantum/VQE/chemistrygen.py
paddle_quantum/VQE/chemistrysub.py
paddle_quantum/VQE/h2.xyz
paddle_quantum/VQE/example/h2.xyz
paddle_quantum/VQE/example/main.py
paddle_quantum/VQSD/HGenerator.py
paddle_quantum/VQSD/Paddle_VQSD.py
paddle_quantum/VQSD/example/main.py
paddle_quantum/ansatz/__init__.py
paddle_quantum/ansatz/circuit.py
paddle_quantum/ansatz/container.py
paddle_quantum/ansatz/layer.py
paddle_quantum/ansatz/vans.py
paddle_quantum/backend/__init__.py
paddle_quantum/backend/density_matrix.py
paddle_quantum/backend/quleaf.py
paddle_quantum/backend/state_vector.py
paddle_quantum/backend/unitary_matrix.py
paddle_quantum/biocomputing/__init__.py
paddle_quantum/biocomputing/algorithm.py
paddle_quantum/biocomputing/data_loader.py
paddle_quantum/biocomputing/mj_matrix.txt
paddle_quantum/biocomputing/operators.py
paddle_quantum/biocomputing/protein.py
paddle_quantum/biocomputing/visualize.py
paddle_quantum/channel/__init__.py
paddle_quantum/channel/base.py
paddle_quantum/channel/common.py
paddle_quantum/channel/custom.py
paddle_quantum/channel/representation.py
paddle_quantum/channel/functional/__init__.py
paddle_quantum/channel/functional/common.py
paddle_quantum/data_analysis/power_flow.py
paddle_quantum/data_analysis/rand_num.py
paddle_quantum-2.4.0.dist-info/LICENSE
paddle_quantum-2.4.0.dist-info/METADATA
paddle_quantum-2.4.0.dist-info/WHEEL
paddle_quantum-2.4.0.dist-info/top_level.txt
paddle_quantum-2.4.0.dist-info/RECORD
