Metadata-Version: 2.1
Name: paddle-quantum
Version: 2.4.0
Summary: Paddle Quantum is a quantum machine learning (QML) toolkit developed based on Baidu PaddlePaddle.
Home-page: http://qml.baidu.com
Author: Institute for Quantum Computing, Baidu INC.
Author-email: qml@baidu.com
Project-URL: Documentation, https://qml.baidu.com/api/introduction.html
Project-URL: Source, https://github.com/PaddlePaddle/Quantum/
Project-URL: Tracker, https://github.com/PaddlePaddle/Quantum/issues
Classifier: Programming Language :: Python :: 3
Classifier: License :: OSI Approved :: Apache Software License
Classifier: Operating System :: OS Independent
Requires-Python: >=3.6, <4
License-File: LICENSE
Requires-Dist: paddlepaddle (<=2.3.0,>=2.2.0)
Requires-Dist: protobuf (<=3.20.1,>=3.1.0)
Requires-Dist: qcompute
Requires-Dist: networkx (>=2.5)
Requires-Dist: matplotlib (>=3.3.0)
Requires-Dist: scipy
Requires-Dist: tqdm
Requires-Dist: openfermion
Requires-Dist: paddlenlp
Requires-Dist: opencv-python
Requires-Dist: scikit-learn
Requires-Dist: fastdtw
Requires-Dist: cvxpy
Requires-Dist: rich
Requires-Dist: imbalanced-learn
Requires-Dist: pyscf ; platform_system == "Linux" or platform_system == "Darwin"
